Workbook

Sheet 所有者权益变动表
B1: 所有者权益变动表（适用执行企业会计准则的一般企业）
X2: 会企04表 单位：元
B3: 纳税人识别号 | C3: =IF(#REF!="","",#REF!) -> #REF! | D3: 纳税人名称 | E3: =IF(#REF!="","",#REF!) -> #REF! | G3: 所属期起 | H3: =IF(#REF!="","",#REF!) -> #REF! | I3: 所属期止 | J3: =IF(#REF!="","",#REF!) -> #REF!
B4: 项目 | C4: 本年金额 | N4: 上年金额
C5: 实收资本(或股本) | D5: 其他权益工具 | G5: 资本公积 | H5: 减：库存股 | I5: 其他综合收益 | J5: 专项储备 | K5: 盈余公积 | L5: 未分配利润 | M5: 所有者权益合计 | N5: 实收资本(或股本) | O5: 其他权益工具 | R5: 资本公积 | S5: 减：库存股 | T5: 其他综合收益 | U5: 专项储备 | V5: 盈余公积 | W5: 未分配利润 | X5: 所有者权益合计
D6: 优先股 | E6: 永续债 | F6: 其他 | O6: 优先股 | P6: 永续债 | Q6: 其他
B7: 一、上年年末余额 | C7: 0 | D7: 0 | E7: 0 | F7: 0 | G7: 0 | H7: 0 | I7: 0 | J7: 0 | K7: 0 | L7: 0 | M7: =ROUND(所有者权益变动表!C7+所有者权益变动表!G7-所有者权益变动表!H7+I7+J7+所有者权益变动表!K7+所有者权益变动表!L7+D7+E7+F7,2) -> 0 | N7: 0 | O7: 0 | P7: 0 | Q7: 0 | R7: 0 | S7: 0 | T7: 0 | U7: 0 | V7: 0 | W7: 0 | X7: =ROUND(所有者权益变动表!N7+所有者权益变动表!R7-所有者权益变动表!S7+T7+U7+所有者权益变动表!V7+所有者权益变动表!W7+O7+P7+Q7,2) -> 0
B8: 加：会计政策变更 | C8: 0 | D8: 0 | E8: 0 | F8: 0 | G8: 0 | H8: 0 | I8: 0 | J8: 0 | K8: 0 | L8: 0 | M8: =ROUND(所有者权益变动表!C8+所有者权益变动表!G8-所有者权益变动表!H8+I8+J8+所有者权益变动表!K8+所有者权益变动表!L8+D8+E8+F8,2) -> 0 | N8: 0 | O8: 0 | P8: 0 | Q8: 0 | R8: 0 | S8: 0 | T8: 0 | U8: 0 | V8: 0 | W8: 0 | X8: =ROUND(所有者权益变动表!N8+所有者权益变动表!R8-所有者权益变动表!S8+T8+U8+所有者权益变动表!V8+所有者权益变动表!W8+O8+P8+Q8,2) -> 0
B9: 前期差错更正 | C9: 0 | D9: 0 | E9: 0 | F9: 0 | G9: 0 | H9: 0 | I9: 0 | J9: 0 | K9: 0 | L9: 0 | M9: =ROUND(所有者权益变动表!C9+所有者权益变动表!G9-所有者权益变动表!H9+I9+J9+所有者权益变动表!K9+所有者权益变动表!L9+D9+E9+F9,2) -> 0 | N9: 0 | O9: 0 | P9: 0 | Q9: 0 | R9: 0 | S9: 0 | T9: 0 | U9: 0 | V9: 0 | W9: 0 | X9: =ROUND(所有者权益变动表!N9+所有者权益变动表!R9-所有者权益变动表!S9+T9+U9+所有者权益变动表!V9+所有者权益变动表!W9+O9+P9+Q9,2) -> 0
B10: 其他 | C10: 0 | D10: 0 | E10: 0 | F10: 0 | G10: 0 | H10: 0 | I10: 0 | J10: 0 | K10: 0 | L10: 0 | M10: =ROUND(所有者权益变动表!C10+所有者权益变动表!G10-所有者权益变动表!H10+I10+J10+所有者权益变动表!K10+所有者权益变动表!L10+D10+E10+F10,2) -> 0 | N10: 0 | O10: 0 | P10: 0 | Q10: 0 | R10: 0 | S10: 0 | T10: 0 | U10: 0 | V10: 0 | W10: 0 | X10: =ROUND(所有者权益变动表!N10+所有者权益变动表!R10-所有者权益变动表!S10+T10+U10+所有者权益变动表!V10+所有者权益变动表!W10+O10+P10+Q10,2) -> 0
B11: 二、本年年初余额 | C11: =ROUND(C7+C8+C9+C10,2) -> 0 | D11: =ROUND(D7+D8+D9+D10,2) -> 0 | E11: =ROUND(E7+E8+E9+E10,2) -> 0 | F11: =ROUND(F7+F8+F9+F10,2) -> 0 | G11: =ROUND(G7+G8+G9+G10,2) -> 0 | H11: =ROUND(H7+H8+H9+H10,2) -> 0 | I11: =ROUND(I7+I8+I9+I10,2) -> 0 | J11: =ROUND(J7+J8+J9+J10,2) -> 0 | ... L11: =ROUND(L7+L8+L9+L10,2) -> 0 | M11: =ROUND(所有者权益变动表!C11+所有者权益变动表!G11-所有者权益变动表!H11+I11+J11+所有者权益变动表!K11+所有者权益变动表!L11+D11+E11+F11,2) -> 0 | N11: =ROUND(N7+N8+N9+N10,2) -> 0 | O11: =ROUND(O7+O8+O9+O10,2) -> 0 | P11: =ROUND(P7+P8+P9+P10,2) -> 0 | Q11: =ROUND(Q7+Q8+Q9+Q10,2) -> 0 | R11: =ROUND(R7+R8+R9+R10,2) -> 0 | S11: =ROUND(S7+S8+S9+S10,2) -> 0 | T11: =ROUND(T7+T8+T9+T10,2) -> 0 | U11: =ROUND(U7+U8+U9+U10,2) -> 0 | ... W11: =ROUND(W7+W8+W9+W10,2) -> 0 | X11: =ROUND(所有者权益变动表!N11+所有者权益变动表!R11-所有者权益变动表!S11+T11+U11+所有者权益变动表!V11+所有者权益变动表!W11+O11+P11+Q11,2) -> 0
B12: 三、本年增减变动金额（减少以“-”号填列） | C12: =ROUND(C13+C14+C19+C23,2) -> 0 | D12: =ROUND(D13+D14+D19+D23,2) -> 0 | E12: =ROUND(E13+E14+E19+E23,2) -> 0 | F12: =ROUND(F13+F14+F19+F23,2) -> 0 | G12: =ROUND(G13+G14+G19+G23,2) -> 0 | H12: =ROUND(H13+H14+H19+H23,2) -> 0 | I12: =ROUND(I13+I14+I19+I23,2) -> 0 | J12: =ROUND(J13+J14+J19+J23,2) -> 0 | ... L12: =ROUND(L13+L14+L19+L23,2) -> 0 | M12: =ROUND(所有者权益变动表!C12+所有者权益变动表!G12-所有者权益变动表!H12+I12+J12+所有者权益变动表!K12+所有者权益变动表!L12+D12+E12+F12,2) -> 0 | N12: =ROUND(N13+N14+N19+N23,2) -> 0 | O12: =ROUND(O13+O14+O19+O23,2) -> 0 | P12: =ROUND(P13+P14+P19+P23,2) -> 0 | Q12: =ROUND(Q13+Q14+Q19+Q23,2) -> 0 | R12: =ROUND(R13+R14+R19+R23,2) -> 0 | S12: =ROUND(S13+S14+S19+S23,2) -> 0 | T12: =ROUND(T13+T14+T19+T23,2) -> 0 | U12: =ROUND(U13+U14+U19+U23,2) -> 0 | ... W12: =ROUND(W13+W14+W19+W23,2) -> 0 | X12: =ROUND(所有者权益变动表!N12+所有者权益变动表!R12-所有者权益变动表!S12+T12+U12+所有者权益变动表!V12+所有者权益变动表!W12+O12+P12+Q12,2) -> 0
B13: （一）综合收益总额 | C13: 0 | D13: 0 | E13: 0 | F13: 0 | G13: 0 | H13: 0 | I13: 0 | J13: 0 | K13: 0 | L13: 0 | M13: =ROUND(所有者权益变动表!C13+所有者权益变动表!G13-所有者权益变动表!H13+I13+J13+所有者权益变动表!K13+所有者权益变动表!L13+D13+E13+F13,2) -> 0 | N13: 0 | O13: 0 | P13: 0 | Q13: 0 | R13: 0 | S13: 0 | T13: 0 | U13: 0 | V13: 0 | W13: 0 | X13: =ROUND(所有者权益变动表!N13+所有者权益变动表!R13-所有者权益变动表!S13+T13+U13+所有者权益变动表!V13+所有者权益变动表!W13+O13+P13+Q13,2) -> 0
B14: （二）所有者投入和减少资本 | C14: =ROUND(所有者权益变动表!C15+所有者权益变动表!C16+所有者权益变动表!C17+所有者权益变动表!C18,2) -> 0 | D14: =ROUND(所有者权益变动表!D15+所有者权益变动表!D16+所有者权益变动表!D17+所有者权益变动表!D18,2) -> 0 | E14: =ROUND(所有者权益变动表!E15+所有者权益变动表!E16+所有者权益变动表!E17+所有者权益变动表!E18,2) -> 0 | F14: =ROUND(所有者权益变动表!F15+所有者权益变动表!F16+所有者权益变动表!F17+所有者权益变动表!F18,2) -> 0 | G14: =ROUND(所有者权益变动表!G15+所有者权益变动表!G16+所有者权益变动表!G17+所有者权益变动表!G18,2) -> 0 | H14: =ROUND(所有者权益变动表!H15+所有者权益变动表!H16+所有者权益变动表!H17+所有者权益变动表!H18,2) -> 0 | I14: =ROUND(所有者权益变动表!I15+所有者权益变动表!I16+所有者权益变动表!I17+所有者权益变动表!I18,2) -> 0 | J14: =ROUND(所有者权益变动表!J15+所有者权益变动表!J16+所有者权益变动表!J17+所有者权益变动表!J18,2) -> 0 | ... L14: =ROUND(所有者权益变动表!L15+所有者权益变动表!L16+所有者权益变动表!L17+所有者权益变动表!L18,2) -> 0 | M14: =ROUND(所有者权益变动表!C14+所有者权益变动表!G14-所有者权益变动表!H14+I14+J14+所有者权益变动表!K14+所有者权益变动表!L14+D14+E14+F14,2) -> 0 | N14: =ROUND(所有者权益变动表!N15+所有者权益变动表!N16+所有者权益变动表!N17+所有者权益变动表!N18,2) -> 0 | O14: =ROUND(所有者权益变动表!O15+所有者权益变动表!O16+所有者权益变动表!O17+所有者权益变动表!O18,2) -> 0 | P14: =ROUND(所有者权益变动表!P15+所有者权益变动表!P16+所有者权益变动表!P17+所有者权益变动表!P18,2) -> 0 | Q14: =ROUND(所有者权益变动表!Q15+所有者权益变动表!Q16+所有者权益变动表!Q17+所有者权益变动表!Q18,2) -> 0 | R14: =ROUND(所有者权益变动表!R15+所有者权益变动表!R16+所有者权益变动表!R17+所有者权益变动表!R18,2) -> 0 | S14: =ROUND(所有者权益变动表!S15+所有者权益变动表!S16+所有者权益变动表!S17+所有者权益变动表!S18,2) -> 0 | T14: =ROUND(所有者权益变动表!T15+所有者权益变动表!T16+所有者权益变动表!T17+所有者权益变动表!T18,2) -> 0 | U14: =ROUND(所有者权益变动表!U15+所有者权益变动表!U16+所有者权益变动表!U17+所有者权益变动表!U18,2) -> 0 | ... W14: =ROUND(所有者权益变动表!W15+所有者权益变动表!W16+所有者权益变动表!W17+所有者权益变动表!W18,2) -> 0 | X14: =ROUND(所有者权益变动表!N14+所有者权益变动表!R14-所有者权益变动表!S14+T14+U14+所有者权益变动表!V14+所有者权益变动表!W14+O14+P14+Q14,2) -> 0
B15: 1.所有者投入的普通股 | C15: 0 | D15: 0 | E15: 0 | F15: 0 | G15: 0 | H15: 0 | I15: 0 | J15: 0 | K15: 0 | L15: 0 | M15: =ROUND(所有者权益变动表!C15+所有者权益变动表!G15-所有者权益变动表!H15+I15+J15+所有者权益变动表!K15+所有者权益变动表!L15+D15+E15+F15,2) -> 0 | N15: 0 | O15: 0 | P15: 0 | Q15: 0 | R15: 0 | S15: 0 | T15: 0 | U15: 0 | V15: 0 | W15: 0 | X15: =ROUND(所有者权益变动表!N15+所有者权益变动表!R15-所有者权益变动表!S15+T15+U15+所有者权益变动表!V15+所有者权益变动表!W15+O15+P15+Q15,2) -> 0
B16: 2.其他权益工具持有者投入资本 | C16: 0 | D16: 0 | E16: 0 | F16: 0 | G16: 0 | H16: 0 | I16: 0 | J16: 0 | K16: 0 | L16: 0 | M16: =ROUND(所有者权益变动表!C16+所有者权益变动表!G16-所有者权益变动表!H16+I16+J16+所有者权益变动表!K16+所有者权益变动表!L16+D16+E16+F16,2) -> 0 | N16: 0 | O16: 0 | P16: 0 | Q16: 0 | R16: 0 | S16: 0 | T16: 0 | U16: 0 | V16: 0 | W16: 0 | X16: =ROUND(所有者权益变动表!N16+所有者权益变动表!R16-所有者权益变动表!S16+T16+U16+所有者权益变动表!V16+所有者权益变动表!W16+O16+P16+Q16,2) -> 0
B17: 3.股份支付计入所有者权益的金额 | C17: 0 | D17: 0 | E17: 0 | F17: 0 | G17: 0 | H17: 0 | I17: 0 | J17: 0 | K17: 0 | L17: 0 | M17: =ROUND(所有者权益变动表!C17+所有者权益变动表!G17-所有者权益变动表!H17+I17+J17+所有者权益变动表!K17+所有者权益变动表!L17+D17+E17+F17,2) -> 0 | N17: 0 | O17: 0 | P17: 0 | Q17: 0 | R17: 0 | S17: 0 | T17: 0 | U17: 0 | V17: 0 | W17: 0 | X17: =ROUND(所有者权益变动表!N17+所有者权益变动表!R17-所有者权益变动表!S17+T17+U17+所有者权益变动表!V17+所有者权益变动表!W17+O17+P17+Q17,2) -> 0
B18: 4.其他 | C18: 0 | D18: 0 | E18: 0 | F18: 0 | G18: 0 | H18: 0 | I18: 0 | J18: 0 | K18: 0 | L18: 0 | M18: =ROUND(所有者权益变动表!C18+所有者权益变动表!G18-所有者权益变动表!H18+I18+J18+所有者权益变动表!K18+所有者权益变动表!L18+D18+E18+F18,2) -> 0 | N18: 0 | O18: 0 | P18: 0 | Q18: 0 | R18: 0 | S18: 0 | T18: 0 | U18: 0 | V18: 0 | W18: 0 | X18: =ROUND(所有者权益变动表!N18+所有者权益变动表!R18-所有者权益变动表!S18+T18+U18+所有者权益变动表!V18+所有者权益变动表!W18+O18+P18+Q18,2) -> 0
B19: （三）利润分配 | C19: =ROUND(所有者权益变动表!C20+所有者权益变动表!C21+所有者权益变动表!C22,2) -> 0 | D19: =ROUND(所有者权益变动表!D20+所有者权益变动表!D21+所有者权益变动表!D22,2) -> 0 | E19: =ROUND(所有者权益变动表!E20+所有者权益变动表!E21+所有者权益变动表!E22,2) -> 0 | F19: =ROUND(所有者权益变动表!F20+所有者权益变动表!F21+所有者权益变动表!F22,2) -> 0 | G19: =ROUND(所有者权益变动表!G20+所有者权益变动表!G21+所有者权益变动表!G22,2) -> 0 | H19: =ROUND(所有者权益变动表!H20+所有者权益变动表!H21+所有者权益变动表!H22,2) -> 0 | I19: =ROUND(所有者权益变动表!I20+所有者权益变动表!I21+所有者权益变动表!I22,2) -> 0 | J19: =ROUND(所有者权益变动表!J20+所有者权益变动表!J21+所有者权益变动表!J22,2) -> 0 | ... L19: =ROUND(所有者权益变动表!L20+所有者权益变动表!L21+所有者权益变动表!L22,2) -> 0 | M19: =ROUND(所有者权益变动表!C19+所有者权益变动表!G19-所有者权益变动表!H19+I19+J19+所有者权益变动表!K19+所有者权益变动表!L19+D19+E19+F19,2) -> 0 | N19: =ROUND(所有者权益变动表!N20+所有者权益变动表!N21+所有者权益变动表!N22,2) -> 0 | O19: =ROUND(所有者权益变动表!O20+所有者权益变动表!O21+所有者权益变动表!O22,2) -> 0 | P19: =ROUND(所有者权益变动表!P20+所有者权益变动表!P21+所有者权益变动表!P22,2) -> 0 | Q19: =ROUND(所有者权益变动表!Q20+所有者权益变动表!Q21+所有者权益变动表!Q22,2) -> 0 | R19: =ROUND(所有者权益变动表!R20+所有者权益变动表!R21+所有者权益变动表!R22,2) -> 0 | S19: =ROUND(所有者权益变动表!S20+所有者权益变动表!S21+所有者权益变动表!S22,2) -> 0 | T19: =ROUND(所有者权益变动表!T20+所有者权益变动表!T21+所有者权益变动表!T22,2) -> 0 | U19: =ROUND(所有者权益变动表!U20+所有者权益变动表!U21+所有者权益变动表!U22,2) -> 0 | ... W19: =ROUND(所有者权益变动表!W20+所有者权益变动表!W21+所有者权益变动表!W22,2) -> 0 | X19: =ROUND(所有者权益变动表!N19+所有者权益变动表!R19-所有者权益变动表!S19+T19+U19+所有者权益变动表!V19+所有者权益变动表!W19+O19+P19+Q19,2) -> 0
B20: 1.提取盈余公积 | C20: 0 | D20: 0 | E20: 0 | F20: 0 | G20: 0 | H20: 0 | I20: 0 | J20: 0 | K20: 0 | L20: 0 | M20: =ROUND(所有者权益变动表!C20+所有者权益变动表!G20-所有者权益变动表!H20+I20+J20+所有者权益变动表!K20+所有者权益变动表!L20+D20+E20+F20,2) -> 0 | N20: 0 | O20: 0 | P20: 0 | Q20: 0 | R20: 0 | S20: 0 | T20: 0 | U20: 0 | V20: 0 | W20: 0 | X20: =ROUND(所有者权益变动表!N20+所有者权益变动表!R20-所有者权益变动表!S20+T20+U20+所有者权益变动表!V20+所有者权益变动表!W20+O20+P20+Q20,2) -> 0
B21: 2.对所有者（或股东）的分配 | C21: 0 | D21: 0 | E21: 0 | F21: 0 | G21: 0 | H21: 0 | I21: 0 | J21: 0 | K21: 0 | L21: 0 | M21: =ROUND(所有者权益变动表!C21+所有者权益变动表!G21-所有者权益变动表!H21+I21+J21+所有者权益变动表!K21+所有者权益变动表!L21+D21+E21+F21,2) -> 0 | N21: 0 | O21: 0 | P21: 0 | Q21: 0 | R21: 0 | S21: 0 | T21: 0 | U21: 0 | V21: 0 | W21: 0 | X21: =ROUND(所有者权益变动表!N21+所有者权益变动表!R21-所有者权益变动表!S21+T21+U21+所有者权益变动表!V21+所有者权益变动表!W21+O21+P21+Q21,2) -> 0
B22: 3.其他 | C22: 0 | D22: 0 | E22: 0 | F22: 0 | G22: 0 | H22: 0 | I22: 0 | J22: 0 | K22: 0 | L22: 0 | M22: =ROUND(所有者权益变动表!C22+所有者权益变动表!G22-所有者权益变动表!H22+I22+J22+所有者权益变动表!K22+所有者权益变动表!L22+D22+E22+F22,2) -> 0 | N22: 0 | O22: 0 | P22: 0 | Q22: 0 | R22: 0 | S22: 0 | T22: 0 | U22: 0 | V22: 0 | W22: 0 | X22: =ROUND(所有者权益变动表!N22+所有者权益变动表!R22-所有者权益变动表!S22+T22+U22+所有者权益变动表!V22+所有者权益变动表!W22+O22+P22+Q22,2) -> 0
B23: （四）所有者权益内部结转 | C23: =ROUND(所有者权益变动表!C24+所有者权益变动表!C25+所有者权益变动表!C26+所有者权益变动表!C27+所有者权益变动表!C28+所有者权益变动表!C29,2) -> 0 | D23: =ROUND(所有者权益变动表!D24+所有者权益变动表!D25+所有者权益变动表!D26+所有者权益变动表!D27+所有者权益变动表!D28+所有者权益变动表!D29,2) -> 0 | E23: =ROUND(所有者权益变动表!E24+所有者权益变动表!E25+所有者权益变动表!E26+所有者权益变动表!E27+所有者权益变动表!E28+所有者权益变动表!E29,2) -> 0 | F23: =ROUND(所有者权益变动表!F24+所有者权益变动表!F25+所有者权益变动表!F26+所有者权益变动表!F27+所有者权益变动表!F28+所有者权益变动表!F29,2) -> 0 | G23: =ROUND(所有者权益变动表!G24+所有者权益变动表!G25+所有者权益变动表!G26+所有者权益变动表!G27+所有者权益变动表!G28+所有者权益变动表!G29,2) -> 0 | H23: =ROUND(所有者权益变动表!H24+所有者权益变动表!H25+所有者权益变动表!H26+所有者权益变动表!H27+所有者权益变动表!H28+所有者权益变动表!H29,2) -> 0 | I23: =ROUND(所有者权益变动表!I24+所有者权益变动表!I25+所有者权益变动表!I26+所有者权益变动表!I27+所有者权益变动表!I28+所有者权益变动表!I29,2) -> 0 | J23: =ROUND(所有者权益变动表!J24+所有者权益变动表!J25+所有者权益变动表!J26+所有者权益变动表!J27+所有者权益变动表!J28+所有者权益变动表!J29,2) -> 0 | ... L23: =ROUND(所有者权益变动表!L24+所有者权益变动表!L25+所有者权益变动表!L26+所有者权益变动表!L27+所有者权益变动表!L28+所有者权益变动表!L29,2) -> 0 | M23: =ROUND(所有者权益变动表!C23+所有者权益变动表!G23-所有者权益变动表!H23+I23+J23+所有者权益变动表!K23+所有者权益变动表!L23+D23+E23+F23,2) -> 0 | N23: =ROUND(所有者权益变动表!N24+所有者权益变动表!N25+所有者权益变动表!N26+所有者权益变动表!N27+所有者权益变动表!N28+所有者权益变动表!N29,2) -> 0 | O23: =ROUND(所有者权益变动表!O24+所有者权益变动表!O25+所有者权益变动表!O26+所有者权益变动表!O27+所有者权益变动表!O28+所有者权益变动表!O29,2) -> 0 | P23: =ROUND(所有者权益变动表!P24+所有者权益变动表!P25+所有者权益变动表!P26+所有者权益变动表!P27+所有者权益变动表!P28+所有者权益变动表!P29,2) -> 0 | Q23: =ROUND(所有者权益变动表!Q24+所有者权益变动表!Q25+所有者权益变动表!Q26+所有者权益变动表!Q27+所有者权益变动表!Q28+所有者权益变动表!Q29,2) -> 0 | R23: =ROUND(所有者权益变动表!R24+所有者权益变动表!R25+所有者权益变动表!R26+所有者权益变动表!R27+所有者权益变动表!R28+所有者权益变动表!R29,2) -> 0 | S23: =ROUND(所有者权益变动表!S24+所有者权益变动表!S25+所有者权益变动表!S26+所有者权益变动表!S27+所有者权益变动表!S28+所有者权益变动表!S29,2) -> 0 | T23: =ROUND(所有者权益变动表!T24+所有者权益变动表!T25+所有者权益变动表!T26+所有者权益变动表!T27+所有者权益变动表!T28+所有者权益变动表!T29,2) -> 0 | U23: =ROUND(所有者权益变动表!U24+所有者权益变动表!U25+所有者权益变动表!U26+所有者权益变动表!U27+所有者权益变动表!U28+所有者权益变动表!U29,2) -> 0 | ... W23: =ROUND(所有者权益变动表!W24+所有者权益变动表!W25+所有者权益变动表!W26+所有者权益变动表!W27+所有者权益变动表!W28+所有者权益变动表!W29,2) -> 0 | X23: =ROUND(所有者权益变动表!N23+所有者权益变动表!R23-所有者权益变动表!S23+T23+U23+所有者权益变动表!V23+所有者权益变动表!W23+O23+P23+Q23,2) -> 0
B24: 1.资本公积转增资本(或股本) | C24: 0 | D24: 0 | E24: 0 | F24: 0 | G24: 0 | H24: 0 | I24: 0 | J24: 0 | K24: 0 | L24: 0 | M24: =ROUND(所有者权益变动表!C24+所有者权益变动表!G24-所有者权益变动表!H24+I24+J24+所有者权益变动表!K24+所有者权益变动表!L24+D24+E24+F24,2) -> 0 | N24: 0 | O24: 0 | P24: 0 | Q24: 0 | R24: 0 | S24: 0 | T24: 0 | U24: 0 | V24: 0 | W24: 0 | X24: =ROUND(所有者权益变动表!N24+所有者权益变动表!R24-所有者权益变动表!S24+T24+U24+所有者权益变动表!V24+所有者权益变动表!W24+O24+P24+Q24,2) -> 0
B25: 2.盈余公积转增资本(或股本) | C25: 0 | D25: 0 | E25: 0 | F25: 0 | G25: 0 | H25: 0 | I25: 0 | J25: 0 | K25: 0 | L25: 0 | M25: =ROUND(所有者权益变动表!C25+所有者权益变动表!G25-所有者权益变动表!H25+I25+J25+所有者权益变动表!K25+所有者权益变动表!L25+D25+E25+F25,2) -> 0 | N25: 0 | O25: 0 | P25: 0 | Q25: 0 | R25: 0 | S25: 0 | T25: 0 | U25: 0 | V25: 0 | W25: 0 | X25: =ROUND(所有者权益变动表!N25+所有者权益变动表!R25-所有者权益变动表!S25+T25+U25+所有者权益变动表!V25+所有者权益变动表!W25+O25+P25+Q25,2) -> 0
B26: 3.盈余公积弥补亏损 | C26: 0 | D26: 0 | E26: 0 | F26: 0 | G26: 0 | H26: 0 | I26: 0 | J26: 0 | K26: 0 | L26: 0 | M26: =ROUND(所有者权益变动表!C26+所有者权益变动表!G26-所有者权益变动表!H26+I26+J26+所有者权益变动表!K26+所有者权益变动表!L26+D26+E26+F26,2) -> 0 | N26: 0 | O26: 0 | P26: 0 | Q26: 0 | R26: 0 | S26: 0 | T26: 0 | U26: 0 | V26: 0 | W26: 0 | X26: =ROUND(所有者权益变动表!N26+所有者权益变动表!R26-所有者权益变动表!S26+T26+U26+所有者权益变动表!V26+所有者权益变动表!W26+O26+P26+Q26,2) -> 0
B27: 4.设定收益计划变动额结转留存收益 | C27: 0 | D27: 0 | E27: 0 | F27: 0 | G27: 0 | H27: 0 | I27: 0 | J27: 0 | K27: 0 | L27: 0 | M27: =ROUND(所有者权益变动表!C27+所有者权益变动表!G27-所有者权益变动表!H27+I27+J27+所有者权益变动表!K27+所有者权益变动表!L27+D27+E27+F27,2) -> 0 | N27: 0 | O27: 0 | P27: 0 | Q27: 0 | R27: 0 | S27: 0 | T27: 0 | U27: 0 | V27: 0 | W27: 0 | X27: =ROUND(所有者权益变动表!N27+所有者权益变动表!R27-所有者权益变动表!S27+T27+U27+所有者权益变动表!V27+所有者权益变动表!W27+O27+P27+Q27,2) -> 0
B28: 5.其他综合收益结转留存收益 | C28: 0 | D28: 0 | E28: 0 | F28: 0 | G28: 0 | H28: 0 | I28: 0 | J28: 0 | K28: 0 | L28: 0 | M28: =ROUND(所有者权益变动表!C28+所有者权益变动表!G28-所有者权益变动表!H28+I28+J28+所有者权益变动表!K28+所有者权益变动表!L28+D28+E28+F28,2) -> 0 | N28: 0 | O28: 0 | P28: 0 | Q28: 0 | R28: 0 | S28: 0 | T28: 0 | U28: 0 | V28: 0 | W28: 0 | X28: =ROUND(所有者权益变动表!N28+所有者权益变动表!R28-所有者权益变动表!S28+T28+U28+所有者权益变动表!V28+所有者权益变动表!W28+O28+P28+Q28,2) -> 0
B29: 6.其他 | C29: 0 | D29: 0 | E29: 0 | F29: 0 | G29: 0 | H29: 0 | I29: 0 | J29: 0 | K29: 0 | L29: 0 | M29: =ROUND(所有者权益变动表!C29+所有者权益变动表!G29-所有者权益变动表!H29+I29+J29+所有者权益变动表!K29+所有者权益变动表!L29+D29+E29+F29,2) -> 0 | N29: 0 | O29: 0 | P29: 0 | Q29: 0 | R29: 0 | S29: 0 | T29: 0 | U29: 0 | V29: 0 | W29: 0 | X29: =ROUND(所有者权益变动表!N29+所有者权益变动表!R29-所有者权益变动表!S29+T29+U29+所有者权益变动表!V29+所有者权益变动表!W29+O29+P29+Q29,2) -> 0
B30: 四、本年年末余额 | C30: =ROUND(所有者权益变动表!C11+所有者权益变动表!C12,2) -> 0 | D30: =ROUND(所有者权益变动表!D11+所有者权益变动表!D12,2) -> 0 | E30: =ROUND(所有者权益变动表!E11+所有者权益变动表!E12,2) -> 0 | F30: =ROUND(所有者权益变动表!F11+所有者权益变动表!F12,2) -> 0 | G30: =ROUND(所有者权益变动表!G11+所有者权益变动表!G12,2) -> 0 | H30: =ROUND(所有者权益变动表!H11+所有者权益变动表!H12,2) -> 0 | I30: =ROUND(所有者权益变动表!I11+所有者权益变动表!I12,2) -> 0 | J30: =ROUND(所有者权益变动表!J11+所有者权益变动表!J12,2) -> 0 | ... L30: =ROUND(所有者权益变动表!L11+所有者权益变动表!L12,2) -> 0 | M30: =ROUND(所有者权益变动表!C30+所有者权益变动表!G30-所有者权益变动表!H30+I30+J30+所有者权益变动表!K30+所有者权益变动表!L30+D30+E30+F30,2) -> 0 | N30: =ROUND(所有者权益变动表!N11+所有者权益变动表!N12,2) -> 0 | O30: =ROUND(所有者权益变动表!O11+所有者权益变动表!O12,2) -> 0 | P30: =ROUND(所有者权益变动表!P11+所有者权益变动表!P12,2) -> 0 | Q30: =ROUND(所有者权益变动表!Q11+所有者权益变动表!Q12,2) -> 0 | R30: =ROUND(所有者权益变动表!R11+所有者权益变动表!R12,2) -> 0 | S30: =ROUND(所有者权益变动表!S11+所有者权益变动表!S12,2) -> 0 | T30: =ROUND(所有者权益变动表!T11+所有者权益变动表!T12,2) -> 0 | U30: =ROUND(所有者权益变动表!U11+所有者权益变动表!U12,2) -> 0 | ... W30: =ROUND(所有者权益变动表!W11+所有者权益变动表!W12,2) -> 0 | X30: =ROUND(所有者权益变动表!N30+所有者权益变动表!R30-所有者权益变动表!S30+T30+U30+所有者权益变动表!V30+所有者权益变动表!W30+O30+P30+Q30,2) -> 0

Sheet 一般企业_已执行
